loopia_update_ip/__init__.py
loopia_update_ip/loopia_update_ip.py
loopia_update_ip/lib/ExternalIPMonitor.py
loopia_update_ip/lib/LoopiaAPI.py
loopia_update_ip/lib/Mailer.py
loopia_update_ip/lib/StreamToLogger.py
loopia_update_ip/lib/__init__.py
loopia_update_ip/lib/get_external_ip.py
loopia_update_ip-0.5.5.dist-info/LICENSE
loopia_update_ip-0.5.5.dist-info/METADATA
loopia_update_ip-0.5.5.dist-info/WHEEL
loopia_update_ip-0.5.5.dist-info/entry_points.txt
loopia_update_ip-0.5.5.dist-info/top_level.txt
loopia_update_ip-0.5.5.dist-info/RECORD
