Metadata-Version: 2.1
Name: loopia-update-ip
Version: 0.5.5
Summary: Application to keep DNS records updated when external IP-address change using the Loopia-API for the domain provider Loopia
Home-page: https://gitlab.com/loopia-update-ip
Author: Niklas Melin
Author-email: niklasme@pm.me
Classifier: Development Status :: 4 - Beta
Classifier: Programming Language :: Python :: 3
Classifier: License :: OSI Approved :: MIT License
Classifier: Operating System :: OS Independent
Requires-Python: >=3.11
License-File: LICENSE
Requires-Dist: setuptools
Requires-Dist: wheel
Requires-Dist: confuse
Requires-Dist: tldextract
